tests/__init__.py
tests/test_masker.py
tests/test_numerical_scalers.py
zorro_df/__init__.py
zorro_df/mask_dataframe.py
zorro_df/numerical_scalers.py
zorro_df-1.1.1.dist-info/LICENSE.txt
zorro_df-1.1.1.dist-info/METADATA
zorro_df-1.1.1.dist-info/WHEEL
zorro_df-1.1.1.dist-info/top_level.txt
zorro_df-1.1.1.dist-info/RECORD
