Metadata-Version: 2.1
Name: zorro-df
Version: 1.1.1
Summary: Package to mask pd.DataFrame data
Home-page: https://github.com/epw505/zorro_df
Author: Ned Webster
Author-email: edwardpwebster@gmail.com
License: UNKNOWN
Platform: UNKNOWN
Classifier: Programming Language :: Python :: 3
Classifier: License :: OSI Approved :: MIT License
Classifier: Operating System :: OS Independent
